{
  "version": "7",
  "dialect": "postgresql",
  "entries": [
    {
      "idx": 0,
      "version": "7",
      "when": 1776405678577,
      "tag": "0000_yielding_ender_wiggin",
      "breakpoints": true
    },
    {
      "idx": 1,
      "version": "7",
      "when": 1776405882547,
      "tag": "0001_dashing_paibok",
      "breakpoints": true
    },
    {
      "idx": 2,
      "version": "7",
      "when": 1776455801192,
      "tag": "0002_add_analysis_kind_parent",
      "breakpoints": true
    }
  ]
}
